semanticli/__init__.py
semanticli/__main__.py
semanticli/cli/cli.py
semanticli/cli/parser_setup.py
semanticli/model/__init__.py
semanticli/model/inference.py
semanticli/model/install.py
semanticli/utils/__init__.py
semanticli/utils/logger.py
semanticli-0.1.3.dist-info/LICENSE
semanticli-0.1.3.dist-info/METADATA
semanticli-0.1.3.dist-info/WHEEL
semanticli-0.1.3.dist-info/entry_points.txt
semanticli-0.1.3.dist-info/top_level.txt
semanticli-0.1.3.dist-info/RECORD
